MANIFEST.in
README.txt
setup.cfg
setup.py
docs/HISTORY.txt
horae/__init__.py
horae.notification.egg-info/PKG-INFO
horae.notification.egg-info/SOURCES.txt
horae.notification.egg-info/dependency_links.txt
horae.notification.egg-info/entry_points.txt
horae.notification.egg-info/namespace_packages.txt
horae.notification.egg-info/not-zip-safe
horae.notification.egg-info/requires.txt
horae.notification.egg-info/top_level.txt
horae/notification/__init__.py
horae/notification/configure.zcml
horae/notification/interfaces.py
horae/notification/notification.py
horae/notification/resource.py
horae/notification/subscription.py
horae/notification/viewlets.py
horae/notification/views.py
horae/notification/locales/horae.notification.pot
horae/notification/locales/de/LC_MESSAGES/horae.notification.mo
horae/notification/locales/de/LC_MESSAGES/horae.notification.po
horae/notification/static/notification.css
horae/notification/static/notification.js
horae/notification/templates/notifications.cpt
horae/notification/viewlet_templates/notifications.cpt